pythanos/__init__.py
pythanos-0.1.dist-info/METADATA
pythanos-0.1.dist-info/WHEEL
pythanos-0.1.dist-info/top_level.txt
pythanos-0.1.dist-info/RECORD
