Metadata-Version: 2.1
Name: pythanos
Version: 0.1
Summary: The aim of this package is to create a pipeline for data analysis and further extends to machine learning
Home-page: http://github.com/umar895/pythanos
Author: Umar
Author-email: m.umar.hameed@outlook.com
License: MIT
Platform: UNKNOWN
